build_tools/changelog.py
build_tools/check_backticks.py
build_tools/make_release.py
build_tools/nb_json_formatter.py
docs/source/Makefile
docs/source/about.rst
docs/source/api_reference.rst
docs/source/changelog.rst
docs/source/changelog_header_template.rst
docs/source/conf.py
docs/source/developer_guide.rst
docs/source/developers.rst
docs/source/estimator_overview.md
docs/source/examples.rst
docs/source/get_involved.rst
docs/source/get_started.rst
docs/source/glossary.rst
docs/source/index.rst
docs/source/installation.rst
docs/source/make.bat
docs/source/related_software.rst
docs/source/roadmap.rst
docs/source/roadmap_2021.rst
docs/source/symlink_examples.sh
docs/source/tutorials.rst
docs/source/users.rst
docs/source/_static/css/custom.css
docs/source/_static/css/fields.css
docs/source/_static/js/dynamic_table.js
docs/source/_templates/class.rst
docs/source/_templates/class_with_call.rst
docs/source/_templates/function.rst
docs/source/_templates/layout.html
docs/source/_templates/numpydoc_docstring.rst
docs/source/about/_mission.rst
docs/source/about/artwork.rst
docs/source/about/citation.md
docs/source/about/contributors.md
docs/source/about/funding.rst
docs/source/about/history.rst
docs/source/about/mission.rst
docs/source/about/showcase.rst
docs/source/about/team.rst
docs/source/api_reference/alignment.rst
docs/source/api_reference/base.rst
docs/source/api_reference/benchmarking.rst
docs/source/api_reference/classification.rst
docs/source/api_reference/clustering.rst
docs/source/api_reference/data_format.rst
docs/source/api_reference/datasets.rst
docs/source/api_reference/deployment.rst
docs/source/api_reference/detection.rst
docs/source/api_reference/dists_kernels.rst
docs/source/api_reference/exceptions.rst
docs/source/api_reference/forecasting.rst
docs/source/api_reference/param_est.rst
docs/source/api_reference/performance_metrics.rst
docs/source/api_reference/pipeline.rst
docs/source/api_reference/regression.rst
sktime-0.39.0.dist-info/licenses/LICENSE
sktime-0.39.0.dist-info/METADATA
sktime-0.39.0.dist-info/WHEEL
sktime-0.39.0.dist-info/top_level.txt
sktime-0.39.0.dist-info/RECORD
