Metadata-Version: 2.4
Name: sktime
Version: 0.39.0
Summary: A unified framework for machine learning with time series
Author-email: sktime developers <sktime.toolbox@gmail.com>
Maintainer: Felix Hirwa Nshuti, Franz Király, Marc Rovira, Ugochukwu Onyeka
Maintainer-email: sktime developers <sktime.toolbox@gmail.com>
License: BSD 3-Clause License
Project-URL: API Reference, https://www.sktime.net/en/stable/api_reference.html
Project-URL: Documentation, https://www.sktime.net
Project-URL: Download, https://pypi.org/project/sktime/#files
Project-URL: Homepage, https://www.sktime.net
Project-URL: Release Notes, https://www.sktime.net/en/stable/changelog.html
Project-URL: Repository, https://github.com/sktime/sktime
Keywords: data-mining,data-science,forecasting,machine-learning,scikit-learn,time-series,time-series-analysis,time-series-classification,time-series-regression
Classifier: Intended Audience :: Developers
Classifier: Intended Audience :: Science/Research
Classifier: License :: OSI Approved :: BSD License
Classifier: Operating System :: MacOS
Classifier: Operating System :: Microsoft :: Windows
Classifier: Operating System :: POSIX
Classifier: Operating System :: Unix
Classifier: Programming Language :: Python
Classifier: Programming Language :: Python :: 3 :: Only
Classifier: Programming Language :: Python :: 3.10
Classifier: Programming Language :: Python :: 3.11
Classifier: Programming Language :: Python :: 3.12
Classifier: Programming Language :: Python :: 3.13
Classifier: Topic :: Scientific/Engineering
Classifier: Topic :: Software Development
Requires-Python: <3.14,>=3.10
License-File: LICENSE
Requires-Dist: joblib<1.6,>=1.2.0
Requires-Dist: numpy<2.4,>=1.21
Requires-Dist: packaging
Requires-Dist: pandas<2.4.0,>=1.1
Requires-Dist: scikit-base<0.13.0,>=0.6.1
Requires-Dist: scikit-learn<1.8.0,>=0.24
Requires-Dist: scipy<2.0.0,>=1.2
Provides-Extra: all-extras
Requires-Dist: arch<7.3.0,>=5.6; python_version < "3.13" and extra == "all-extras"
Requires-Dist: autots<0.7,>=0.6.1; extra == "all-extras"
Requires-Dist: cloudpickle; python_version < "3.13" and extra == "all-extras"
Requires-Dist: dash!=2.9.0; python_version < "3.13" and extra == "all-extras"
Requires-Dist: dask<2025.2.1,>2024.8.2; (extra == "dataframe" and python_version < "3.13") and extra == "all-extras"
Requires-Dist: dtw-python; python_version < "3.13" and extra == "all-extras"
Requires-Dist: gluonts>=0.9; python_version < "3.13" and extra == "all-extras"
Requires-Dist: h5py; python_version < "3.12" and extra == "all-extras"
Requires-Dist: hmmlearn>=0.2.7; python_version < "3.11" and extra == "all-extras"
Requires-Dist: holidays; python_version < "3.13" and extra == "all-extras"
Requires-Dist: matplotlib!=3.9.1,>=3.3.2; python_version < "3.13" and extra == "all-extras"
Requires-Dist: numba<0.63,>=0.53; extra == "all-extras"
Requires-Dist: optuna<4.5; extra == "all-extras"
Requires-Dist: pmdarima!=1.8.1,<3.0.0,>=1.8; python_version < "3.12" and extra == "all-extras"
Requires-Dist: polars[pandas]<2.0,>=0.20; python_version < "3.13" and extra == "all-extras"
Requires-Dist: prophet>=1.1; python_version < "3.12" and extra == "all-extras"
Requires-Dist: pycatch22<0.4.6; python_version < "3.13" and extra == "all-extras"
Requires-Dist: pyod>=0.8; python_version < "3.11" and extra == "all-extras"
Requires-Dist: pyts<0.14.0; python_version < "3.12" and extra == "all-extras"
Requires-Dist: ray>=2.40.0; python_version < "3.13" and extra == "all-extras"
Requires-Dist: scikit-optimize; python_version < "3.13" and extra == "all-extras"
Requires-Dist: scikit_posthocs>=0.6.5; python_version < "3.13" and extra == "all-extras"
Requires-Dist: seaborn>=0.11; python_version < "3.13" and extra == "all-extras"
Requires-Dist: simdkalman; extra == "all-extras"
Requires-Dist: skforecast<0.15,>=0.12.1; python_version < "3.13" and extra == "all-extras"
Requires-Dist: skpro<2.10.0,>=2; extra == "all-extras"
Requires-Dist: statsforecast<2.1.0,>=1.0.0; python_version < "3.13" and extra == "all-extras"
Requires-Dist: statsmodels>=0.12.1; python_version < "3.13" and extra == "all-extras"
Requires-Dist: tensorflow<2.20,>=2; python_version < "3.13" and extra == "all-extras"
Requires-Dist: tsfresh>=0.17; python_version < "3.12" and extra == "all-extras"
Requires-Dist: tslearn!=0.6.0,<0.7.0,>=0.5.2; python_version < "3.11" and extra == "all-extras"
Requires-Dist: xarray; python_version < "3.13" and extra == "all-extras"
Provides-Extra: all-extras-pandas2
Requires-Dist: arch<7.1.0,>=5.6; python_version < "3.13" and extra == "all-extras-pandas2"
Requires-Dist: autots<0.7,>=0.6.1; python_version < "3.13" and extra == "all-extras-pandas2"
Requires-Dist: cloudpickle; python_version < "3.13" and extra == "all-extras-pandas2"
Requires-Dist: dash!=2.9.0; python_version < "3.13" and extra == "all-extras-pandas2"
Requires-Dist: dask<2025.2.1,>2024.8.2; (extra == "dataframe" and python_version < "3.13") and extra == "all-extras-pandas2"
Requires-Dist: dtw-python; python_version < "3.13" and extra == "all-extras-pandas2"
Requires-Dist: gluonts>=0.9; python_version < "3.13" and extra == "all-extras-pandas2"
Requires-Dist: h5py; python_version < "3.12" and extra == "all-extras-pandas2"
Requires-Dist: hmmlearn>=0.2.7; python_version < "3.11" and extra == "all-extras-pandas2"
Requires-Dist: holidays; python_version < "3.13" and extra == "all-extras-pandas2"
Requires-Dist: matplotlib!=3.9.1,>=3.3.2; python_version < "3.13" and extra == "all-extras-pandas2"
Requires-Dist: numba<0.63,>=0.53; extra == "all-extras-pandas2"
Requires-Dist: optuna<4.5; extra == "all-extras-pandas2"
Requires-Dist: pmdarima!=1.8.1,<3.0.0,>=1.8; python_version < "3.12" and extra == "all-extras-pandas2"
Requires-Dist: polars[pandas]<2.0,>=0.20; python_version < "3.13" and extra == "all-extras-pandas2"
Requires-Dist: prophet>=1.1; python_version < "3.12" and extra == "all-extras-pandas2"
Requires-Dist: pycatch22<0.4.6; python_version < "3.13" and extra == "all-extras-pandas2"
Requires-Dist: pyod>=0.8; python_version < "3.11" and extra == "all-extras-pandas2"
Requires-Dist: ray>=2.40.0; python_version < "3.13" and extra == "all-extras-pandas2"
Requires-Dist: scikit_posthocs>=0.6.5; python_version < "3.13" and extra == "all-extras-pandas2"
Requires-Dist: seaborn>=0.11; python_version < "3.13" and extra == "all-extras-pandas2"
Requires-Dist: simdkalman; extra == "all-extras-pandas2"
Requires-Dist: skforecast<0.15,>=0.12.1; python_version < "3.13" and extra == "all-extras-pandas2"
Requires-Dist: skpro<2.10.0,>=2; extra == "all-extras-pandas2"
Requires-Dist: statsforecast<2.1.0,>=1.0.0; python_version < "3.13" and extra == "all-extras-pandas2"
Requires-Dist: statsmodels>=0.12.1; python_version < "3.13" and extra == "all-extras-pandas2"
Requires-Dist: tensorflow<2.20,>=2; python_version < "3.13" and extra == "all-extras-pandas2"
Requires-Dist: tsfresh>=0.17; python_version < "3.12" and extra == "all-extras-pandas2"
Requires-Dist: tslearn!=0.6.0,<0.7.0,>=0.5.2; python_version < "3.11" and extra == "all-extras-pandas2"
Requires-Dist: xarray; python_version < "3.13" and extra == "all-extras-pandas2"
Provides-Extra: alignment
Requires-Dist: dtaidistance<2.4; python_version < "3.13" and extra == "alignment"
Requires-Dist: dtw-python<1.6,>=1.3; python_version < "3.13" and extra == "alignment"
Requires-Dist: numba<0.63,>=0.53; extra == "alignment"
Provides-Extra: annotation
Requires-Dist: hmmlearn<0.4,>=0.2.7; python_version < "3.13" and extra == "annotation"
Requires-Dist: numba<0.63,>=0.53; extra == "annotation"
Requires-Dist: pyod<1.2,>=0.8; python_version < "3.12" and extra == "annotation"
Provides-Extra: classification
Requires-Dist: numba<0.63,>=0.53; extra == "classification"
Requires-Dist: tensorflow<2.20,>=2; python_version < "3.13" and extra == "classification"
Requires-Dist: tsfresh<0.21,>=0.17; python_version < "3.12" and extra == "classification"
Provides-Extra: clustering
Requires-Dist: networkx<3.5; extra == "clustering"
Requires-Dist: numba<0.63,>=0.53; extra == "clustering"
Requires-Dist: tslearn!=0.6.0,<0.7.0,>=0.5.2; python_version < "3.12" and extra == "clustering"
Requires-Dist: ts2vg<1.3; (python_version < "3.13" and platform_machine != "aarch64") and extra == "clustering"
Provides-Extra: detection
Requires-Dist: hmmlearn<0.4,>=0.2.7; python_version < "3.13" and extra == "detection"
Requires-Dist: numba<0.63,>=0.53; extra == "detection"
Requires-Dist: pyod<1.2,>=0.8; python_version < "3.12" and extra == "detection"
Provides-Extra: forecasting
Requires-Dist: arch<7.1,>=5.6; python_version < "3.13" and extra == "forecasting"
Requires-Dist: autots<0.7,>=0.6.1; python_version < "3.13" and extra == "forecasting"
Requires-Dist: pmdarima!=1.8.1,<2.1,>=1.8; python_version < "3.12" and extra == "forecasting"
Requires-Dist: prophet<1.2,>=1.1; python_version < "3.13" and extra == "forecasting"
Requires-Dist: skforecast<0.15,>=0.12.1; python_version < "3.13" and extra == "forecasting"
Requires-Dist: skpro<2.10.0,>=2; extra == "forecasting"
Requires-Dist: statsforecast<2.1.0,>=1.0.0; python_version < "3.13" and extra == "forecasting"
Requires-Dist: statsmodels<0.15,>=0.12.1; python_version < "3.13" and extra == "forecasting"
Provides-Extra: networks
Requires-Dist: tensorflow<2.20,>=2; python_version < "3.13" and extra == "networks"
Provides-Extra: param-est
Requires-Dist: seasonal<0.4,>=0.3.1; python_version < "3.13" and extra == "param-est"
Requires-Dist: statsmodels<0.15,>=0.12.1; python_version < "3.13" and extra == "param-est"
Provides-Extra: regression
Requires-Dist: numba<0.63,>=0.53; extra == "regression"
Requires-Dist: tensorflow<2.20,>=2; python_version < "3.13" and extra == "regression"
Provides-Extra: transformations
Requires-Dist: holidays<0.59,>=0.29; python_version < "3.13" and extra == "transformations"
Requires-Dist: numba<0.63,>=0.53; extra == "transformations"
Requires-Dist: pycatch22<0.4.6,>=0.4; python_version < "3.13" and extra == "transformations"
Requires-Dist: simdkalman; extra == "transformations"
Requires-Dist: statsmodels<0.15,>=0.12.1; python_version < "3.13" and extra == "transformations"
Requires-Dist: tsfresh<0.21,>=0.17; python_version < "3.12" and extra == "transformations"
Provides-Extra: dev
Requires-Dist: backoff; extra == "dev"
Requires-Dist: httpx; extra == "dev"
Requires-Dist: pre-commit; extra == "dev"
Requires-Dist: pytest; extra == "dev"
Requires-Dist: pytest-randomly; extra == "dev"
Requires-Dist: pytest-timeout; extra == "dev"
Requires-Dist: pytest-xdist; extra == "dev"
Requires-Dist: wheel; extra == "dev"
Provides-Extra: docs
Requires-Dist: jupyter; extra == "docs"
Requires-Dist: myst-parser; extra == "docs"
Requires-Dist: nbsphinx>=0.8.6; extra == "docs"
Requires-Dist: numpydoc; extra == "docs"
Requires-Dist: pydata-sphinx-theme; extra == "docs"
Requires-Dist: Sphinx!=7.2.0,<9.0.0; extra == "docs"
Requires-Dist: sphinx-copybutton; extra == "docs"
Requires-Dist: sphinx-design<0.7.0; extra == "docs"
Requires-Dist: sphinx-gallery<0.20.0; extra == "docs"
Requires-Dist: sphinx-issues<6.0.0; extra == "docs"
Requires-Dist: tabulate; extra == "docs"
Provides-Extra: tests
Requires-Dist: pytest<8.5,>=7.4; extra == "tests"
Requires-Dist: pytest-randomly<4.1,>=3.15; extra == "tests"
Requires-Dist: pytest-timeout<2.5,>=2.1; extra == "tests"
Requires-Dist: pytest-xdist<3.9,>=3.3; extra == "tests"
Provides-Extra: binder
Requires-Dist: jupyter; extra == "binder"
Requires-Dist: skchange; extra == "binder"
Provides-Extra: cython-extras
Requires-Dist: mrseql<0.0.3; extra == "cython-extras"
Requires-Dist: mrsqm; python_version < "3.11" and extra == "cython-extras"
Requires-Dist: numba<0.63; extra == "cython-extras"
Provides-Extra: datasets
Requires-Dist: huggingface-hub; extra == "datasets"
Requires-Dist: rdata; extra == "datasets"
Requires-Dist: requests; extra == "datasets"
Provides-Extra: dl
Requires-Dist: FrEIA; python_version < "3.12" and extra == "dl"
Requires-Dist: neuralforecast<1.8.0,>=1.6.4; python_version < "3.11" and extra == "dl"
Requires-Dist: peft<0.14.0,>=0.10.0; python_version < "3.12" and extra == "dl"
Requires-Dist: tensorflow<2.20,>=2; python_version < "3.13" and extra == "dl"
Requires-Dist: torch; (sys_platform != "darwin" or python_version != "3.13") and extra == "dl"
Requires-Dist: transformers[torch]<4.41.0; python_version < "3.12" and extra == "dl"
Requires-Dist: pykan<0.2.9,>=0.2.1; python_version > "3.9.7" and extra == "dl"
Requires-Dist: pytorch-forecasting<1.5.0,>=1.0.0; (sys_platform != "darwin" or python_version != "3.13") and extra == "dl"
Requires-Dist: lightning>=2.0; python_version < "3.12" and extra == "dl"
Requires-Dist: gluonts>=0.14.3; python_version < "3.12" and extra == "dl"
Requires-Dist: einops>0.7.0; python_version < "3.12" and extra == "dl"
Requires-Dist: huggingface-hub>=0.23.0; python_version < "3.12" and extra == "dl"
Requires-Dist: accelerate; extra == "dl"
Requires-Dist: tqdm; extra == "dl"
Requires-Dist: hydra-core; python_version < "3.13" and extra == "dl"
Provides-Extra: mlflow
Requires-Dist: mlflow<4.0; extra == "mlflow"
Provides-Extra: mlflow2
Requires-Dist: mlflow<3.0; extra == "mlflow2"
Provides-Extra: mlflow-tests
Requires-Dist: boto3; extra == "mlflow-tests"
Requires-Dist: botocore; extra == "mlflow-tests"
Requires-Dist: mlflow<4.0; extra == "mlflow-tests"
Requires-Dist: moto; extra == "mlflow-tests"
Provides-Extra: notebooks
Requires-Dist: matplotlib; extra == "notebooks"
Requires-Dist: numpy<2; extra == "notebooks"
Requires-Dist: pmdarima; extra == "notebooks"
Requires-Dist: seaborn; extra == "notebooks"
Requires-Dist: tbats; extra == "notebooks"
Requires-Dist: dtw-python; extra == "notebooks"
Requires-Dist: prophet; extra == "notebooks"
Requires-Dist: pytorch-forecasting; extra == "notebooks"
Requires-Dist: skpro; extra == "notebooks"
Requires-Dist: statsforecast; extra == "notebooks"
Provides-Extra: numpy1
Requires-Dist: numpy<2.0.0; extra == "numpy1"
Provides-Extra: pandas1
Requires-Dist: pandas<2.0.0; extra == "pandas1"
Provides-Extra: compatibility-tests
Requires-Dist: catboost; python_version < "3.13" and extra == "compatibility-tests"
Provides-Extra: dependencies-lowest
Requires-Dist: numpy==1.21.0; extra == "dependencies-lowest"
Requires-Dist: pandas==1.1.0; extra == "dependencies-lowest"
Requires-Dist: scikit-learn==0.24.0; extra == "dependencies-lowest"
Requires-Dist: scipy==1.4.0; extra == "dependencies-lowest"
Provides-Extra: dependencies-lower
Requires-Dist: numpy==1.25.0; extra == "dependencies-lower"
Requires-Dist: pandas==2.0.2; extra == "dependencies-lower"
Requires-Dist: scikit-learn==1.3.0; extra == "dependencies-lower"
Requires-Dist: scipy==1.10.1; extra == "dependencies-lower"
Dynamic: license-file
